pdfparse/__init__.py
pdfparse/pdfid.py
pdfparse/pdfparse.py
pdfparse/pdfparser.py
pdfparse-1.3.dist-info/DESCRIPTION.rst
pdfparse-1.3.dist-info/METADATA
pdfparse-1.3.dist-info/RECORD
pdfparse-1.3.dist-info/WHEEL
pdfparse-1.3.dist-info/entry_points.txt
pdfparse-1.3.dist-info/metadata.json
pdfparse-1.3.dist-info/top_level.txt
