Metadata-Version: 2.0
Name: pdfparse
Version: 1.3
Summary: to parse pdf and search for malicious file
Home-page: https://github.com/boddumanohar/pdfparse
Author: boddu
Author-email: b.manu199@icloud.com
License: UNKNOWN
Download-URL: https://github.com/boddumanohar/pdfparse/archive/0.1.tar.gz
Keywords: viruspdf,malicious,pdfparse
Platform: UNKNOWN
